odoo/addons/ssi_web_widget_many2onereference_clickable/README.rst
odoo/addons/ssi_web_widget_many2onereference_clickable/__init__.py
odoo/addons/ssi_web_widget_many2onereference_clickable/__manifest__.py
odoo/addons/ssi_web_widget_many2onereference_clickable/static/description/icon.png
odoo/addons/ssi_web_widget_many2onereference_clickable/static/src/css/ssi_web_widget_many2onereference_clickable.scss
odoo/addons/ssi_web_widget_many2onereference_clickable/static/src/js/ssi_web_widget_many2onereference_clickable.js
odoo/addons/ssi_web_widget_many2onereference_clickable/views/assets.xml
odoo14_addon_ssi_web_widget_many2onereference_clickable-14.0.1.0.0.dist-info/METADATA
odoo14_addon_ssi_web_widget_many2onereference_clickable-14.0.1.0.0.dist-info/WHEEL
odoo14_addon_ssi_web_widget_many2onereference_clickable-14.0.1.0.0.dist-info/top_level.txt
odoo14_addon_ssi_web_widget_many2onereference_clickable-14.0.1.0.0.dist-info/RECORD
